Workbook
Name anos: SIMULADOR!$D$16
Name aporte: SIMULADOR!$D$15
Name atrimonio: SIMULADOR!$D$18
Name patrimonio: SIMULADOR!$D$18
Name rendimento_carteira: SIMULADOR!$D$10
Name salario: SIMULADOR!$D$9
Name sugestao_invest: SIMULADOR!$D$12
Name taxa_mensal: SIMULADOR!$D$17

Sheet SIMULADOR
B8: CONFIGURAÇÕES
B9: Salário | D9: 2800
B10: Rendimento Carteira | D10: 0.01
B11: Percentual do Salário Para Investir | D11: 0.15
B12: Sugestão de Investimento | D12: =salario*D11 -> 420
B14: INVESTIMENTO MENSAL
B15: Quanto investir por mês? | D15: 420
B16: Por quantos anos? | D16: 5
B17: Taxa de rendimento mensal? | D17: 0.0108
B18: Patrimonio acumulado? | D18: =FV(taxa_mensal,anos*12,aporte*-1) -> 35197.688
B19: Dividendos mensais? | D19: =patrimonio*rendimento_carteira -> 351.97688
B21: CENÁRIOS | D21: DIVIDENDOS
A22: 2 | B22: Quanto em 2 Anos | C22: =FV($D$17,$A22*12,$D$15*-1) -> 11436.963 | D22: =C22*rendimento_carteira -> 114.36963
A23: 5 | B23: Quanto em 5 Anos | C23: =FV($D$17,$A23*12,$D$15*-1) -> 35197.688 | D23: =C23*rendimento_carteira -> 351.97688
A24: 10 | B24: Quanto em 10 Anos | C24: =FV($D$17,$A24*12,$D$15*-1) -> 102252.22 | D24: =C24*rendimento_carteira -> 1022.5222
A25: 20 | B25: Quanto em 20 Anos | C25: =FV($D$17,$A25*12,$D$15*-1) -> 473360.58 | D25: =C25*rendimento_carteira -> 4733.6058
A26: 30 | B26: Quanto em 30 Anos | C26: =FV($D$17,$A26*12,$D$15*-1) -> 1820240 | D26: =C26*rendimento_carteira -> 18202.4
B28: DISTRIBUIÇÃO DO APORTE MENSAL
B29: PERFIL | D29: AGRESSIVO
B31: TIPO DE FII | C31: PERCENTUAL SUGERIDO (%) | D31: VALORES
A32: =$D$29&"-"&B32 -> AGRESSIVO-PAPEL | B32: PAPEL | C32: =VLOOKUP(A32,DATA!B6:E24,4,FALSE) -> 0.5 | D32: =sugestao_invest*C32 -> 210
A33: =$D$29&"-"&B33 -> AGRESSIVO-TIJOLO | B33: TIJOLO | C33: =VLOOKUP(A33,DATA!B7:E25,4,FALSE) -> 0.1 | D33: =sugestao_invest*C33 -> 42
A34: =$D$29&"-"&B34 -> AGRESSIVO-HÍBRIDO | B34: HÍBRIDO | C34: =VLOOKUP(A34,DATA!B8:E26,4,FALSE) -> 0.05 | D34: =sugestao_invest*C34 -> 21
A35: =$D$29&"-"&B35 -> AGRESSIVO-FOF | B35: FOF | C35: =VLOOKUP(A35,DATA!B9:E27,4,FALSE) -> 0.05 | D35: =sugestao_invest*C35 -> 21
A36: =$D$29&"-"&B36 -> AGRESSIVO-DESENVOLVIMENTO | B36: DESENVOLVIMENTO | C36: =VLOOKUP(A36,DATA!B10:E28,4,FALSE) -> 0.2 | D36: =sugestao_invest*C36 -> 84
A37: =$D$29&"-"&B37 -> AGRESSIVO-HOTELARIA | B37: HOTELARIA | C37: =VLOOKUP(A37,DATA!B11:E29,4,FALSE) -> 0.1 | D37: =sugestao_invest*C37 -> 42
A38: =$D$29&"-"&B38 -> AGRESSIVO-TOTAL | B38: TOTAL | D38: =SUM(D32:D37) -> 420

Sheet DATA
B6: CHAVE | C6: PERFIL | D6: TIPO DE FII | E6: %
B7: =C7&"-"&D7 -> CONSERVADOR-PAPEL | C7: CONSERVADOR | D7: PAPEL | E7: 0.3
B8: =C8&"-"&D8 -> CONSERVADOR-TIJOLO | C8: CONSERVADOR | D8: TIJOLO | E8: 0.5
B9: =C9&"-"&D9 -> CONSERVADOR-HÍBRIDO | C9: CONSERVADOR | D9: HÍBRIDO | E9: 0.1
B10: =C10&"-"&D10 -> CONSERVADOR-FOF | C10: CONSERVADOR | D10: FOF | E10: 0.1
B11: =C11&"-"&D11 -> CONSERVADOR-DESENVOLVIMENTO | C11: CONSERVADOR | D11: DESENVOLVIMENTO | E11: 0
B12: =C12&"-"&D12 -> CONSERVADOR-HOTELARIA | C12: CONSERVADOR | D12: HOTELARIA | E12: 0
B13: =C13&"-"&D13 -> MODERADO-PAPEL | C13: MODERADO | D13: PAPEL | E13: 0.32
B14: =C14&"-"&D14 -> MODERADO-TIJOLO | C14: MODERADO | D14: TIJOLO | E14: 0.4
B15: =C15&"-"&D15 -> MODERADO-HÍBRIDO | C15: MODERADO | D15: HÍBRIDO | E15: 0.08
B16: =C16&"-"&D16 -> MODERADO-FOF | C16: MODERADO | D16: FOF | E16: 0.1
B17: =C17&"-"&D17 -> MODERADO-DESENVOLVIMENTO | C17: MODERADO | D17: DESENVOLVIMENTO | E17: 0.05
B18: =C18&"-"&D18 -> MODERADO-HOTELARIA | C18: MODERADO | D18: HOTELARIA | E18: 0.05
... B24: =C24&"-"&D24 -> AGRESSIVO-HOTELARIA | C24: AGRESSIVO | D24: HOTELARIA | E24: 0.1
